sitemap2vector-0.1.0.dist-info/METADATA
sitemap2vector-0.1.0.dist-info/WHEEL
sitemap2vector-0.1.0.dist-info/licenses/LICENSE
sitemap2vector/__init__.py
sitemap2vector/helloworld.py
sitemap2vector-0.1.0.dist-info/RECORD
