Metadata-Version: 2.1
Name: sitemap2vector
Version: 0.1.0
Summary: Default template for PDM package
Author-Email: Michael Edoror <medoror@gmail.com>
License: MIT
Project-URL: Homepage, https://github.com/medoror/sitemap2vector
Project-URL: Issues, https://github.com/medoror/sitemap2vector/issues
Requires-Python: >=3.12
